MANIFEST.in
README.md
requirements.txt
setup.cfg
setup.py
bgapi/__init__.py
bgapi/api.py
bgapi/cmd_def.py
bgapi/module.py
bgapi.egg-info/PKG-INFO
bgapi.egg-info/SOURCES.txt
bgapi.egg-info/dependency_links.txt
bgapi.egg-info/requires.txt
bgapi.egg-info/top_level.txt
test/test_client_server.py