Metadata-Version: 1.1
Name: bgapi
Version: 0.2
Summary: Interface library for BlueGiga BLE112 and BLE113 modules
Home-page: https://github.com/mjbrown/bgapi
Author: Michael Brown
Author-email: mjbrown.droid@gmail.com
License: UNKNOWN
Platform: UNKNOWN
Classifier: Development Status :: 3 - Alpha
Classifier: Intended Audience :: Developers
Classifier: License :: OSI Approved :: Mozilla Public License 2.0 (MPL 2.0)
Classifier: Programming Language :: Python :: 2.6
Classifier: Programming Language :: Python :: 2.7
Classifier: Topic :: Software Development :: Libraries
Classifier: Operating System :: OS Independent
